setup.py
simplestart/__init__.py
simplestart/_app.py
simplestart/launch.py
simplestart.egg-info/PKG-INFO
simplestart.egg-info/SOURCES.txt
simplestart.egg-info/dependency_links.txt
simplestart.egg-info/entry_points.txt
simplestart.egg-info/requires.txt
simplestart.egg-info/top_level.txt
simplestart/static/favicon.ico
simplestart/static/index.html
simplestart/static/assets/index-cd0ed653.css
simplestart/static/assets/index-cd0ed653.css.gz
simplestart/static/assets/index-eeb47016.js
simplestart/static/assets/index-eeb47016.js.gz
simplestart/static/assets/materialdesignicons-webfont-67d24abe.eot
simplestart/static/assets/materialdesignicons-webfont-80bb28b3.woff
simplestart/static/assets/materialdesignicons-webfont-a58ecb54.ttf
simplestart/static/assets/materialdesignicons-webfont-c1c004a9.woff2
simplestart/sub1/server.c
simplestart/sub1/streamsync.c